StatisticalThinkingForThe21stCentury/README.md
StatisticalThinkingForThe21stCentury/__init__.py
StatisticalThinkingForThe21stCentury/__main__.py
StatisticalThinkingForThe21stCentury/file.epub
StatisticalThinkingForThe21stCentury/index.html
StatisticalThinkingForThe21stCentury/css/__init__.py
StatisticalThinkingForThe21stCentury/css/annotations.css
StatisticalThinkingForThe21stCentury/css/main.css
StatisticalThinkingForThe21stCentury/css/normalize.css
StatisticalThinkingForThe21stCentury/css/popup.css
StatisticalThinkingForThe21stCentury/font/__init__.py
StatisticalThinkingForThe21stCentury/font/fontello.eot
StatisticalThinkingForThe21stCentury/font/fontello.svg
StatisticalThinkingForThe21stCentury/font/fontello.ttf
StatisticalThinkingForThe21stCentury/font/fontello.woff
StatisticalThinkingForThe21stCentury/img/__init__.py
StatisticalThinkingForThe21stCentury/img/annotator-glyph-sprite.png
StatisticalThinkingForThe21stCentury/img/annotator-icon-sprite.png
StatisticalThinkingForThe21stCentury/img/apple-touch-icon.png
StatisticalThinkingForThe21stCentury/img/cancelfullscreen.png
StatisticalThinkingForThe21stCentury/img/close.png
StatisticalThinkingForThe21stCentury/img/fullscreen.png
StatisticalThinkingForThe21stCentury/img/loader.gif
StatisticalThinkingForThe21stCentury/img/menu-icon.png
StatisticalThinkingForThe21stCentury/img/save.png
StatisticalThinkingForThe21stCentury/img/saved.png
StatisticalThinkingForThe21stCentury/img/settings-s.png
StatisticalThinkingForThe21stCentury/img/settings.png
StatisticalThinkingForThe21stCentury/img/star.png
StatisticalThinkingForThe21stCentury/js/__init__.py
StatisticalThinkingForThe21stCentury/js/epub.js
StatisticalThinkingForThe21stCentury/js/epub.min.js
StatisticalThinkingForThe21stCentury/js/epub.min.map
StatisticalThinkingForThe21stCentury/js/hooks.min.js
StatisticalThinkingForThe21stCentury/js/hooks.min.map
StatisticalThinkingForThe21stCentury/js/reader.js
StatisticalThinkingForThe21stCentury/js/reader.js.map
statistical_thinking_for_the_21st_century-2024.3.5.0.dist-info/METADATA
statistical_thinking_for_the_21st_century-2024.3.5.0.dist-info/WHEEL
statistical_thinking_for_the_21st_century-2024.3.5.0.dist-info/entry_points.txt
statistical_thinking_for_the_21st_century-2024.3.5.0.dist-info/top_level.txt
statistical_thinking_for_the_21st_century-2024.3.5.0.dist-info/RECORD
